{
  "parent": "minecraft:recipes/root",
  "criteria": {
    "has_the_recipe": {
      "conditions": {
        "recipe": "minecraft:verdant_terracotta_trim"
      },
      "trigger": "minecraft:recipe_unlocked"
    },
    "has_verdant_terracotta": {
      "conditions": {
        "items": [
          {
            "items": [
              "dye_depot:verdant_terracotta"
            ]
          }
        ]
      },
      "trigger": "minecraft:inventory_changed"
    }
  },
  "requirements": [
    [
      "has_verdant_terracotta",
      "has_the_recipe"
    ]
  ],
  "rewards": {
    "recipes": [
      "minecraft:verdant_terracotta_trim"
    ]
  },
  "sends_telemetry_event": false
}